Metadata-Version: 1.1
Name: selector
Version: 0.10.0
Summary: WSGI request delegation. (AKA routing.)
Home-page: http://github.com/lukearno/selector/
Author: Luke Arno
Author-email: luke.arno@gmail.com
License: MIT
Keywords: wsgi delegation routing web http rest webapps
Platform: UNKNOWN
Classifier: Development Status :: 3 - Alpha
Classifier: Environment :: Web Environment
Classifier: Intended Audience :: Developers
Classifier: License :: OSI Approved :: MIT License
Classifier: License :: OSI Approved :: GNU General Public License (GPL)
Classifier: Natural Language :: English
Classifier: Operating System :: OS Independent
Classifier: Programming Language :: Python
Classifier: Topic :: Software Development :: Libraries
Classifier: Topic :: Utilities
